{
    "bookname": "Electron 官方文档多语言电子书",
    "description": "Electron 官方文档多语言电子书",
    "author": "Imfly",
    "keywords": [
        "electron",
        "nodejs",
        "gitbook",
        "ebook",
        "doc"
    ],
    "ignores": ["backup", "_book", "styles", "assets", "node_modules","sources"],
    "homepage": "https://github.com/doc-ebooks/electron-docs-gitbook",
    "license": "MIT",
    "repository": {
        "type": "git",
        "url": "https://github.com/doc-ebooks/electron-docs-gitbook.git"
    },
    "bugs": {
        "url": "https://github.com/doc-ebooks/electron-docs-gitbook/issues"
    },
    "plugins": [
      "baidu",
      "-livereload"
    ],
    "pluginsConfig": {
        "baidu": {
            "token": "acfc5cd60db044270ff996429917c2b7"
        }
    }
}
